README.md
setup.py
src/DMXEnttecPro/__init__.py
src/DMXEnttecPro/controller.py
src/DMXEnttecPro/utils.py
src/DMXEnttecPro.egg-info/PKG-INFO
src/DMXEnttecPro.egg-info/SOURCES.txt
src/DMXEnttecPro.egg-info/dependency_links.txt
src/DMXEnttecPro.egg-info/requires.txt
src/DMXEnttecPro.egg-info/top_level.txt