Metadata-Version: 2.1
Name: DMXEnttecPro
Version: 0.4
Summary: Python control of the Enttec DMX USB Pro
Home-page: UNKNOWN
Author: Paul Barton
Author-email: pablo.barton@gmail.com
License: GPL3
Platform: UNKNOWN
Classifier: Programming Language :: Python :: 3.5
Classifier: Programming Language :: Python :: 3.6
Classifier: Programming Language :: Python :: 3.7
Classifier: License :: OSI Approved :: GNU General Public License v3 (GPLv3)
Classifier: Operating System :: OS Independent
Classifier: Development Status :: 4 - Beta
